LICENSE
MANIFEST.in
README.rst
buildout.cfg
develop.cfg
requirements.txt
setup.py
version.txt
bob/__init__.py
bob.io.matlab.egg-info/PKG-INFO
bob.io.matlab.egg-info/SOURCES.txt
bob.io.matlab.egg-info/dependency_links.txt
bob.io.matlab.egg-info/not-zip-safe
bob.io.matlab.egg-info/requires.txt
bob.io.matlab.egg-info/top_level.txt
bob/io/__init__.py
bob/io/matlab/__init__.py
bob/io/matlab/bobskin.cpp
bob/io/matlab/bobskin.h
bob/io/matlab/file.cpp
bob/io/matlab/file.h
bob/io/matlab/main.cpp
bob/io/matlab/test.py
bob/io/matlab/utils.cpp
bob/io/matlab/utils.h
bob/io/matlab/version.cpp
bob/io/matlab/data/test.mat
bob/io/matlab/data/test_1d.mat
bob/io/matlab/data/test_1d_cplx.mat
bob/io/matlab/data/test_2d.mat
bob/io/matlab/data/test_2d_cplx.mat
bob/io/matlab/data/test_3d.mat
bob/io/matlab/data/test_3d_cplx.mat
bob/io/matlab/data/test_4d.mat
bob/io/matlab/data/test_4d_cplx.mat
bob/io/matlab/data/test_cell.mat
doc/conf.py
doc/guide.rst
doc/index.rst
doc/links.rst
doc/py_api.rst