Metadata-Version: 1.1
Name: bob.io.matlab
Version: 2.0.11
Summary: Handling of Matlab(R) files via bob.io.base
Home-page: http://gitlab.idiap.ch/bob/bob.io.matlab
Author: Andre Anjos
Author-email: andre.anjos@idiap.ch
License: BSD
Platform: UNKNOWN
Classifier: Framework :: Bob
Classifier: Development Status :: 4 - Beta
Classifier: Intended Audience :: Developers
Classifier: License :: OSI Approved :: BSD License
Classifier: Natural Language :: English
Classifier: Programming Language :: Python
Classifier: Programming Language :: Python :: 3
Classifier: Topic :: Software Development :: Libraries :: Python Modules
Classifier: Environment :: Plugins
